odoo/addons/sale_commission_oca/README.rst
odoo/addons/sale_commission_oca/__init__.py
odoo/addons/sale_commission_oca/__manifest__.py
odoo/addons/sale_commission_oca/i18n/es.po
odoo/addons/sale_commission_oca/i18n/it.po
odoo/addons/sale_commission_oca/i18n/ja.po
odoo/addons/sale_commission_oca/i18n/pt_BR.po
odoo/addons/sale_commission_oca/i18n/sale_commission_oca.pot
odoo/addons/sale_commission_oca/i18n/tr.po
odoo/addons/sale_commission_oca/models/__init__.py
odoo/addons/sale_commission_oca/models/sale_order.py
odoo/addons/sale_commission_oca/readme/CONTRIBUTORS.md
odoo/addons/sale_commission_oca/readme/DESCRIPTION.md
odoo/addons/sale_commission_oca/readme/USAGE.md
odoo/addons/sale_commission_oca/security/ir.model.access.csv
odoo/addons/sale_commission_oca/static/description/icon.png
odoo/addons/sale_commission_oca/static/description/icon.svg
odoo/addons/sale_commission_oca/static/description/index.html
odoo/addons/sale_commission_oca/tests/__init__.py
odoo/addons/sale_commission_oca/tests/test_sale_commission.py
odoo/addons/sale_commission_oca/views/sale_order_view.xml
odoo_addon_sale_commission_oca-18.0.1.0.0.6.dist-info/METADATA
odoo_addon_sale_commission_oca-18.0.1.0.0.6.dist-info/WHEEL
odoo_addon_sale_commission_oca-18.0.1.0.0.6.dist-info/top_level.txt
odoo_addon_sale_commission_oca-18.0.1.0.0.6.dist-info/RECORD
